md_ref_checker/__init__.py
md_ref_checker/checker.py
md_ref_checker/cli.py
md_ref_checker/models.py
md_ref_checker/parsers.py
md_ref_checker/utils.py
md_ref_checker-0.2.3.dist-info/METADATA
md_ref_checker-0.2.3.dist-info/WHEEL
md_ref_checker-0.2.3.dist-info/entry_points.txt
md_ref_checker-0.2.3.dist-info/licenses/LICENSE
md_ref_checker-0.2.3.dist-info/RECORD
