Metadata-Version: 2.4
Name: md-ref-checker
Version: 0.2.3
Summary: A tool for checking references in Markdown files
Project-URL: Homepage, https://github.com/chess99/md-ref-checker
Project-URL: Repository, https://github.com/chess99/md-ref-checker.git
Author-email: chess99 <chess99@126.com>
License-Expression: MIT
License-File: LICENSE
Keywords: checker,markdown,obsidian,reference
Classifier: Development Status :: 3 - Alpha
Classifier: Intended Audience :: Developers
Classifier: License :: OSI Approved :: MIT License
Classifier: Programming Language :: Python :: 3
Classifier: Programming Language :: Python :: 3.8
Classifier: Programming Language :: Python :: 3.9
Classifier: Programming Language :: Python :: 3.10
Classifier: Programming Language :: Python :: 3.11
Requires-Python: >=3.8
Requires-Dist: click>=8.0.0
Requires-Dist: markdown-it-py>=3.0.0
Provides-Extra: dev
Requires-Dist: black>=23.0.0; extra == 'dev'
Requires-Dist: mypy>=1.0.0; extra == 'dev'
Requires-Dist: pre-commit>=3.5.0; extra == 'dev'
Requires-Dist: pytest-cov>=4.0.0; extra == 'dev'
Requires-Dist: pytest>=7.0.0; extra == 'dev'
Requires-Dist: ruff>=0.1.0; extra == 'dev'
Requires-Dist: types-click; extra == 'dev'
